cincoconfig/__init__.py
cincoconfig/core.py
cincoconfig/encryption.py
cincoconfig/fields/__init__.py
cincoconfig/fields/bool_field.py
cincoconfig/fields/bytes_field.py
cincoconfig/fields/dict_field.py
cincoconfig/fields/file_field.py
cincoconfig/fields/include_field.py
cincoconfig/fields/instance_method_field.py
cincoconfig/fields/list_field.py
cincoconfig/fields/net_field.py
cincoconfig/fields/number_field.py
cincoconfig/fields/secure_field.py
cincoconfig/fields/string_field.py
cincoconfig/fields/url_field.py
cincoconfig/fields/virtual_field.py
cincoconfig/formats/__init__.py
cincoconfig/formats/bson.py
cincoconfig/formats/json.py
cincoconfig/formats/pickle.py
cincoconfig/formats/xml.py
cincoconfig/formats/yaml.py
cincoconfig/stubs.py
cincoconfig/support.py
cincoconfig/VERSION
cincoconfig/version.py
cincoconfig-0.9.0.dist-info/LICENSE
cincoconfig-0.9.0.dist-info/METADATA
cincoconfig-0.9.0.dist-info/WHEEL
cincoconfig-0.9.0.dist-info/RECORD
