Metadata-Version: 2.1
Name: cincoconfig
Version: 0.9.0
Summary: Universal configuration file parser
Home-page: https://github.com/ameily/cincoconfig
License: ISC
Keywords: config,configuration
Author: Adam Meily
Author-email: meily.adam@gmail.com
Requires-Python: >=3.7,<4.0
Classifier: Development Status :: 4 - Beta
Classifier: Intended Audience :: Developers
Classifier: License :: OSI Approved
Classifier: License :: OSI Approved :: ISC License (ISCL)
Classifier: Natural Language :: English
Classifier: Operating System :: OS Independent
Classifier: Programming Language :: Python
Classifier: Programming Language :: Python :: 3
Classifier: Programming Language :: Python :: 3.7
Classifier: Programming Language :: Python :: 3.8
Classifier: Programming Language :: Python :: 3.9
Classifier: Programming Language :: Python :: 3.10
Classifier: Programming Language :: Python :: 3.11
Classifier: Programming Language :: Python :: 3
Classifier: Topic :: Software Development :: Libraries :: Application Frameworks
Project-URL: Documentation, https://cincoconfig.readthedocs.io/en/latest/
Project-URL: Repository, https://github.com/ameily/cincoconfig
